<?xml version="1.0" encoding="UTF-8" standalone="yes"?>

<item>
<title>[COLOR lime]TEMPORADA 1[/COLOR]</title>
<link>http://</link>
<thumbnail>https://pics.filmaffinity.com/eureka_tv_series-476241319-large.jpg</thumbnail>
<fanart>http://fuertecito.groarl.com/files/2012/07/eurfin1.jpeg</fanart>
</item>

<item>
<title>Capítulo  1</title>
<link>http://streamcloud.eu/cadteyw16g1x/0358_Eur3k4-HDiTunes_1x01_LiNkMaN.avi.html</link>
<thumbnail>https://pics.filmaffinity.com/eureka_tv_series-476241319-large.jpg</thumbnail>
<fanart>http://fuertecito.groarl.com/files/2012/07/eurfin1.jpeg</fanart>
</item>

<item>
<title>Capítulo  2</title>
<link>http://streamcloud.eu/p4i87bt7megx/0358_Eur3k4-HDiTunes_1x02_LiNkMaN.avi.html</link>
<thumbnail>https://pics.filmaffinity.com/eureka_tv_series-476241319-large.jpg</thumbnail>
<fanart>http://fuertecito.groarl.com/files/2012/07/eurfin1.jpeg</fanart>
</item>

<item>
<title>Capítulo  3</title>
<link>http://streamcloud.eu/jvx74tmbi3ew/0358_Eur3k4-HDiTunes_1x03_LiNkMaN.avi.html</link>
<thumbnail>https://pics.filmaffinity.com/eureka_tv_series-476241319-large.jpg</thumbnail>
<fanart>http://fuertecito.groarl.com/files/2012/07/eurfin1.jpeg</fanart>
</item>

<item>
<title>Capítulo  4</title>
<link>http://streamcloud.eu/lfwz4i2coq7d/3vr3k4-.1x04..Castellano.avi.html</link>
<thumbnail>https://pics.filmaffinity.com/eureka_tv_series-476241319-large.jpg</thumbnail>
<fanart>http://fuertecito.groarl.com/files/2012/07/eurfin1.jpeg</fanart>
</item>

<item>
<title>Capítulo  5</title>
<link>http://streamcloud.eu/ueng37clw6d3/0358_Eur3k4-HDiTunes_1x05_LiNkMaN.avi.html</link>
<thumbnail>https://pics.filmaffinity.com/eureka_tv_series-476241319-large.jpg</thumbnail>
<fanart>http://fuertecito.groarl.com/files/2012/07/eurfin1.jpeg</fanart>
</item>

<item>
<title>Capítulo  6</title>
<link>http://streamcloud.eu/cmjycoqmw3q5/3vr3k4-.1x06..Castellano.avi.html</link>
<thumbnail>https://pics.filmaffinity.com/eureka_tv_series-476241319-large.jpg</thumbnail>
<fanart>http://fuertecito.groarl.com/files/2012/07/eurfin1.jpeg</fanart>
</item>

<item>
<title>Capítulo  7</title>
<link>http://streamcloud.eu/fox5q9vdihdn/0358_Eur3k4-HDiTunes_1x07_LiNkMaN.avi.html</link>
<thumbnail>https://pics.filmaffinity.com/eureka_tv_series-476241319-large.jpg</thumbnail>
<fanart>http://fuertecito.groarl.com/files/2012/07/eurfin1.jpeg</fanart>
</item>


<item>
<title>Capítulo  8</title>
<link>http://streamcloud.eu/znb4qt08x1ox/Eureka.1x08.Inteligencia.artificial.avi.html</link>
<thumbnail>https://pics.filmaffinity.com/eureka_tv_series-476241319-large.jpg</thumbnail>
<fanart>http://fuertecito.groarl.com/files/2012/07/eurfin1.jpeg</fanart>
</item>

<item>
<title>Capítulo  9</title>
<link>http://streamcloud.eu/9wmvuk681vxt/3vr3k4-.1x09..Castellano.avi.html</link>
<thumbnail>https://pics.filmaffinity.com/eureka_tv_series-476241319-large.jpg</thumbnail>
<fanart>http://fuertecito.groarl.com/files/2012/07/eurfin1.jpeg</fanart>
</item>

<item>
<title>Capítulo  10</title>
<link>http://streamcloud.eu/ho46u0vx9gde/0358_Eur3k4-HDiTunes_1x10_LiNkMaN.avi.html</link>
<thumbnail>https://pics.filmaffinity.com/eureka_tv_series-476241319-large.jpg</thumbnail>
<fanart>http://fuertecito.groarl.com/files/2012/07/eurfin1.jpeg</fanart>
</item>

<item>
<title>Capítulo  11</title>
<link>http://streamcloud.eu/a1m3v8az4ctf/0358_Eur3k4-HDiTunes_1x11_LiNkMaN.avi.html</link>
<thumbnail>https://pics.filmaffinity.com/eureka_tv_series-476241319-large.jpg</thumbnail>
<fanart>http://fuertecito.groarl.com/files/2012/07/eurfin1.jpeg</fanart>
</item>

<item>
<title>Capítulo  12</title>
<link>http://streamcloud.eu/wkwmmekr2hxr/3vr3k4-.1x12..Castellano.avi.html</link>
<thumbnail>https://pics.filmaffinity.com/eureka_tv_series-476241319-large.jpg</thumbnail>
<fanart>http://fuertecito.groarl.com/files/2012/07/eurfin1.jpeg</fanart>
</item>



<item>
<title>[COLOR lime]TEMPORADA 2[/COLOR]</title>
<link>http://</link>
<thumbnail>https://pics.filmaffinity.com/eureka_tv_series-476241319-large.jpg</thumbnail>
<fanart>http://fuertecito.groarl.com/files/2012/07/eurfin1.jpeg</fanart>
</item>


<item>
<title>Capítulo  1</title>
<link>http://streamcloud.eu/rf84hcu015z3/Eureka.2x01.El.ave.Fenix.avi.html</link>
<thumbnail>https://pics.filmaffinity.com/eureka_tv_series-476241319-large.jpg</thumbnail>
<fanart>http://fuertecito.groarl.com/files/2012/07/eurfin1.jpeg</fanart>
</item>

<item>
<title>Capítulo  2</title>
<link>http://streamcloud.eu/gnyfveh1bip2/Eureka.2x02.Intentarlo.y.volverlo.a.intentar.avi.html</link>
<thumbnail>https://pics.filmaffinity.com/eureka_tv_series-476241319-large.jpg</thumbnail>
<fanart>http://fuertecito.groarl.com/files/2012/07/eurfin1.jpeg</fanart>
</item>

<item>
<title>Capítulo  3</title>
<link>http://streamcloud.eu/0w17pik7kexe/Eureka.2x03.Impredecible.avi.html</link>
<thumbnail>https://pics.filmaffinity.com/eureka_tv_series-476241319-large.jpg</thumbnail>
<fanart>http://fuertecito.groarl.com/files/2012/07/eurfin1.jpeg</fanart>
</item>

<item>
<title>Capítulo  4</title>
<link>http://streamcloud.eu/68wuipvo8uro/Eureka.2x04.Los.juegos.de.la.gente.avi.html</link>
<thumbnail>https://pics.filmaffinity.com/eureka_tv_series-476241319-large.jpg</thumbnail>
<fanart>http://fuertecito.groarl.com/files/2012/07/eurfin1.jpeg</fanart>
</item>

<item>
<title>Capítulo  5</title>
<link>http://streamcloud.eu/mr4v5nj22lsc/Eureka.2x05.La.feria.de.ciencia.avi.html</link>
<thumbnail>https://pics.filmaffinity.com/eureka_tv_series-476241319-large.jpg</thumbnail>
<fanart>http://fuertecito.groarl.com/files/2012/07/eurfin1.jpeg</fanart>
</item>

<item>
<title>Capítulo  6</title>
<link>http://streamcloud.eu/dgg42gsern6w</link>
<thumbnail>https://pics.filmaffinity.com/eureka_tv_series-476241319-large.jpg</thumbnail>
<fanart>http://fuertecito.groarl.com/files/2012/07/eurfin1.jpeg</fanart>
</item>

<item>
<title>Capítulo  7</title>
<link>http://streamcloud.eu/ekq6wxsl3hcf/Eureka.2x07.Reencuentro.familiar.avi.html</link>
<thumbnail>https://pics.filmaffinity.com/eureka_tv_series-476241319-large.jpg</thumbnail>
<fanart>http://fuertecito.groarl.com/files/2012/07/eurfin1.jpeg</fanart>
</item>

<item>
<title>Capítulo  8</title>
<link>http://streamcloud.eu/6vgpq1iox3uy/3vr3k4-.2x08..Castellano.avi.html</link>
<thumbnail>https://pics.filmaffinity.com/eureka_tv_series-476241319-large.jpg</thumbnail>
<fanart>http://fuertecito.groarl.com/files/2012/07/eurfin1.jpeg</fanart>
</item>

<item>
<title>Capítulo  9 </title>
<link>http://streamcloud.eu/lfzt094eu0es/Eureka.2x09.Lo.nunca.visto.avi.html</link>
<thumbnail>https://pics.filmaffinity.com/eureka_tv_series-476241319-large.jpg</thumbnail>
<fanart>http://fuertecito.groarl.com/files/2012/07/eurfin1.jpeg</fanart>
</item>

<item>
<title>Capítulo  10</title>
<link>http://streamcloud.eu/gqhswfbdbqxf/Eureka.2x10.Dios.esta.en.los.detalles.avi.html</link>
<thumbnail>https://pics.filmaffinity.com/eureka_tv_series-476241319-large.jpg</thumbnail>
<fanart>http://fuertecito.groarl.com/files/2012/07/eurfin1.jpeg</fanart>
</item>

<item>
<title>Capítulo  11</title>
<link>http://streamcloud.eu/bagqltjy390z/Eureka.2x11.Devorahombres.avi.html</link>
<thumbnail>https://pics.filmaffinity.com/eureka_tv_series-476241319-large.jpg</thumbnail>
<fanart>http://fuertecito.groarl.com/files/2012/07/eurfin1.jpeg</fanart>
</item>

<item>
<title>Capítulo  12</title>
<link>http://streamcloud.eu/ll079guk7vnk/DC.LGENDS.S02E12.m720p.WEB.DL.mkv.html</link>
<thumbnail>https://pics.filmaffinity.com/eureka_tv_series-476241319-large.jpg</thumbnail>
<fanart>http://fuertecito.groarl.com/files/2012/07/eurfin1.jpeg</fanart>
</item>

<item>
<title>Capítulo  13</title>
<link>http://streamcloud.eu/ysmwp816f36n/3vr3k4-_2x13.avi.html</link>
<thumbnail>https://pics.filmaffinity.com/eureka_tv_series-476241319-large.jpg</thumbnail>
<fanart>http://fuertecito.groarl.com/files/2012/07/eurfin1.jpeg</fanart>
</item>


<item>
<title>[COLOR lime]TEMPORADA 3[/COLOR]</title>
<link>http://</link>
<thumbnail>https://pics.filmaffinity.com/eureka_tv_series-476241319-large.jpg</thumbnail>
<fanart>http://fuertecito.groarl.com/files/2012/07/eurfin1.jpeg</fanart>
</item>


<item>
<title>Capítulo  1</title>
<link>http://streamcloud.eu/hilmagdnc7ku/Eureka.3x01.Rebelde.sin.causa.avi.html</link>
<thumbnail>https://pics.filmaffinity.com/eureka_tv_series-476241319-large.jpg</thumbnail>
<fanart>http://fuertecito.groarl.com/files/2012/07/eurfin1.jpeg</fanart>
</item>


<item>
<title>Capítulo  2</title>
<link>http://streamcloud.eu/v5t8edplfkus/Eureka.3x02.Que.pasa.con.Bob.avi.html</link>
<thumbnail>https://pics.filmaffinity.com/eureka_tv_series-476241319-large.jpg</thumbnail>
<fanart>http://fuertecito.groarl.com/files/2012/07/eurfin1.jpeg</fanart>
</item>


<item>
<title>Capítulo  3</title>
<link>http://streamcloud.eu/8djpicb4h36a/Eureka.3x03.El.mejor.entre.los.falsos.avi.html</link>
<thumbnail>https://pics.filmaffinity.com/eureka_tv_series-476241319-large.jpg</thumbnail>
<fanart>http://fuertecito.groarl.com/files/2012/07/eurfin1.jpeg</fanart>
</item>

<item>
<title>Capítulo  4</title>
<link>http://streamcloud.eu/at4lsd13txh0/Eureka.3x04.Yo.repito.avi.html</link>
<thumbnail>https://pics.filmaffinity.com/eureka_tv_series-476241319-large.jpg</thumbnail>
<fanart>http://fuertecito.groarl.com/files/2012/07/eurfin1.jpeg</fanart>
</item>


<item>
<title>Capítulo  5</title>
<link>http://streamcloud.eu/lihxpta6mkbs/Eureka.3x05.Ensename.la.momia.avi.html</link>
<thumbnail>https://pics.filmaffinity.com/eureka_tv_series-476241319-large.jpg</thumbnail>
<fanart>http://fuertecito.groarl.com/files/2012/07/eurfin1.jpeg</fanart>
</item>


<item>
<title>Capítulo  6</title>
<link>http://streamcloud.eu/wcxqr5q7t3i9</link>
<thumbnail>https://pics.filmaffinity.com/eureka_tv_series-476241319-large.jpg</thumbnail>
<fanart>http://fuertecito.groarl.com/files/2012/07/eurfin1.jpeg</fanart>
</item>


<item>
<title>Capítulo  7</title>
<link>http://streamcloud.eu/oiw7rldbd6ni</link>
<thumbnail>https://pics.filmaffinity.com/eureka_tv_series-476241319-large.jpg</thumbnail>
<fanart>http://fuertecito.groarl.com/files/2012/07/eurfin1.jpeg</fanart>
</item>

<item>
<title>Capítulo  8</title>
<link>http://streamcloud.eu/95zvl4wust38/Eureka.3x08.Del.miedo.a.la.eternidad.avi.html</link>
<thumbnail>https://pics.filmaffinity.com/eureka_tv_series-476241319-large.jpg</thumbnail>
<fanart>http://fuertecito.groarl.com/files/2012/07/eurfin1.jpeg</fanart>
</item>

<item>
<title>Capítulo  9</title>
<link>http://streamcloud.eu/9p7sa8uena1n</link>
<thumbnail>https://pics.filmaffinity.com/eureka_tv_series-476241319-large.jpg</thumbnail>
<fanart>http://fuertecito.groarl.com/files/2012/07/eurfin1.jpeg</fanart>
</item>


<item>
<title>Capítulo  10</title>
<link>http://streamcloud.eu/jsuz5rzi92np</link>
<thumbnail>https://pics.filmaffinity.com/eureka_tv_series-476241319-large.jpg</thumbnail>
<fanart>http://fuertecito.groarl.com/files/2012/07/eurfin1.jpeg</fanart>
</item>


<item>
<title>Capítulo  11</title>
<link>http://streamcloud.eu/dq0qo4feqac6/Eureka.3x11.Locura.y.P.Branas.avi.html</link>
<thumbnail>https://pics.filmaffinity.com/eureka_tv_series-476241319-large.jpg</thumbnail>
<fanart>http://fuertecito.groarl.com/files/2012/07/eurfin1.jpeg</fanart>
</item>

<item>
<title>Capítulo  12</title>
<link>http://streamcloud.eu/vf7hauzhpope/Eureka.3x12.No.es.facil.ser.verde.avi.html</link>
<thumbnail>https://pics.filmaffinity.com/eureka_tv_series-476241319-large.jpg</thumbnail>
<fanart>http://fuertecito.groarl.com/files/2012/07/eurfin1.jpeg</fanart>
</item>


<item>
<title>Capítulo  13</title>
<link>http://streamcloud.eu/ufcks58enzuc</link>
<thumbnail>https://pics.filmaffinity.com/eureka_tv_series-476241319-large.jpg</thumbnail>
<fanart>http://fuertecito.groarl.com/files/2012/07/eurfin1.jpeg</fanart>
</item>


<item>
<title>Capítulo  14</title>
<link>http://streamcloud.eu/9ft2r1dd6ana/Eureka.3x14.La.nave.vive.avi.html</link>
<thumbnail>https://pics.filmaffinity.com/eureka_tv_series-476241319-large.jpg</thumbnail>
<fanart>http://fuertecito.groarl.com/files/2012/07/eurfin1.jpeg</fanart>
</item>


<item>
<title>Capítulo  15</title>
<link>http://streamcloud.eu/imnzn9vgmscl/Eureka.3x15.Una.fiesta.pasada.por.agua.avi.html</link>
<thumbnail>https://pics.filmaffinity.com/eureka_tv_series-476241319-large.jpg</thumbnail>
<fanart>http://fuertecito.groarl.com/files/2012/07/eurfin1.jpeg</fanart>
</item>

<item>
<title>Capítulo  16</title>
<link>http://streamcloud.eu/iqw60uv2nadq/Eureka.3x16.Tu.no.conoces.a.Jack.avi.html</link>
<thumbnail>https://pics.filmaffinity.com/eureka_tv_series-476241319-large.jpg</thumbnail>
<fanart>http://fuertecito.groarl.com/files/2012/07/eurfin1.jpeg</fanart>
</item>

<item>
<title>Capítulo  17</title>
<link>http://streamcloud.eu/jrrdlqvjq1ih</link>
<thumbnail>https://pics.filmaffinity.com/eureka_tv_series-476241319-large.jpg</thumbnail>
<fanart>http://fuertecito.groarl.com/files/2012/07/eurfin1.jpeg</fanart>
</item>

<item>
<title>Capítulo  18</title>
<link>http://streamcloud.eu/oq6tz6xkxz6l/Eureka.3x18.El.que.siembra_cosecha.avi.html</link>
<thumbnail>https://pics.filmaffinity.com/eureka_tv_series-476241319-large.jpg</thumbnail>
<fanart>http://fuertecito.groarl.com/files/2012/07/eurfin1.jpeg</fanart>
</item>


<item>
<title>[COLOR lime]TEMPORADA 5[/COLOR]</title>
<link>http://</link>
<thumbnail>https://pics.filmaffinity.com/eureka_tv_series-476241319-large.jpg</thumbnail>
<fanart>http://fuertecito.groarl.com/files/2012/07/eurfin1.jpeg</fanart>
</item>

<item>
<title>Capítulo  1</title>
<link>http://streamcloud.eu/cup2n5flmj1f/Eureka.5x01.Perdidos.avi.html</link>
<thumbnail>https://pics.filmaffinity.com/eureka_tv_series-476241319-large.jpg</thumbnail>
<fanart>http://fuertecito.groarl.com/files/2012/07/eurfin1.jpeg</fanart>
</item>

<item>
<title>Capítulo  2</title>
<link>http://streamcloud.eu/a0amagusnbwg</link>
<thumbnail>https://pics.filmaffinity.com/eureka_tv_series-476241319-large.jpg</thumbnail>
<fanart>http://fuertecito.groarl.com/files/2012/07/eurfin1.jpeg</fanart>
</item>

<item>
<title>Capítulo  3</title>
<link>http://streamcloud.eu/5yi2u4hrs0p4</link>
<thumbnail>https://pics.filmaffinity.com/eureka_tv_series-476241319-large.jpg</thumbnail>
<fanart>http://fuertecito.groarl.com/files/2012/07/eurfin1.jpeg</fanart>
</item>

<item>
<title>Capítulo  4</title>
<link>http://streamcloud.eu/8rsxwkokj0bn</link>
<thumbnail>https://pics.filmaffinity.com/eureka_tv_series-476241319-large.jpg</thumbnail>
<fanart>http://fuertecito.groarl.com/files/2012/07/eurfin1.jpeg</fanart>
</item>

<item>
<title>Capítulo  5</title>
<link>http://streamcloud.eu/tywatu5gnbf7</link>
<thumbnail>https://pics.filmaffinity.com/eureka_tv_series-476241319-large.jpg</thumbnail>
<fanart>http://fuertecito.groarl.com/files/2012/07/eurfin1.jpeg</fanart>
</item>

<item>
<title>Capítulo  6</title>
<link>http://streamcloud.eu/f4hcprjtrlg2</link>
<thumbnail>https://pics.filmaffinity.com/eureka_tv_series-476241319-large.jpg</thumbnail>
<fanart>http://fuertecito.groarl.com/files/2012/07/eurfin1.jpeg</fanart>
</item>

<item>
<title>Capítulo  7</title>
<link>http://streamcloud.eu/8ey4433zwjqt</link>
<thumbnail>https://pics.filmaffinity.com/eureka_tv_series-476241319-large.jpg</thumbnail>
<fanart>http://fuertecito.groarl.com/files/2012/07/eurfin1.jpeg</fanart>
</item>

<item>
<title>Capítulo  8</title>
<link>http://streamcloud.eu/7bgjbqmvsu1e</link>
<thumbnail>https://pics.filmaffinity.com/eureka_tv_series-476241319-large.jpg</thumbnail>
<fanart>http://fuertecito.groarl.com/files/2012/07/eurfin1.jpeg</fanart>
</item>

<item>
<title>Capítulo  9</title>
<link>http://streamcloud.eu/6gem4r4iug25</link>
<thumbnail>https://pics.filmaffinity.com/eureka_tv_series-476241319-large.jpg</thumbnail>
<fanart>http://fuertecito.groarl.com/files/2012/07/eurfin1.jpeg</fanart>
</item>

<item>
<title>Capítulo  10</title>
<link>http://streamcloud.eu/g9h710u1l0cb</link>
<thumbnail>https://pics.filmaffinity.com/eureka_tv_series-476241319-large.jpg</thumbnail>
<fanart>http://fuertecito.groarl.com/files/2012/07/eurfin1.jpeg</fanart>
</item>

<item>
<title>Capítulo  11</title>
<link>http://streamcloud.eu/4hvnuu3hmxlw</link>
<thumbnail>https://pics.filmaffinity.com/eureka_tv_series-476241319-large.jpg</thumbnail>
<fanart>http://fuertecito.groarl.com/files/2012/07/eurfin1.jpeg</fanart>
</item>

<item>
<title>Capítulo  12</title>
<link>http://streamcloud.eu/gm2myd1lb8un</link>
<thumbnail>https://pics.filmaffinity.com/eureka_tv_series-476241319-large.jpg</thumbnail>
<fanart>http://fuertecito.groarl.com/files/2012/07/eurfin1.jpeg</fanart>
</item>

<item>
<title>Capítulo  13</title>
<link>http://streamcloud.eu/f4vuvq6hyf3t</link>
<thumbnail>https://pics.filmaffinity.com/eureka_tv_series-476241319-large.jpg</thumbnail>
<fanart>http://fuertecito.groarl.com/files/2012/07/eurfin1.jpeg</fanart>
</item>




